pmutt/__init__.py
pmutt/constants.py
pmutt/examples.py
pmutt/cantera/__init__.py
pmutt/cantera/phase.py
pmutt/cantera/reaction.py
pmutt/cantera/units.py
pmutt/chemkin/__init__.py
pmutt/empirical/__init__.py
pmutt/empirical/nasa.py
pmutt/empirical/references.py
pmutt/empirical/shomate.py
pmutt/empirical/zacros.py
pmutt/eos/__init__.py
pmutt/equilibrium/__init__.py
pmutt/equilibrium/_equilibrium.py
pmutt/io/__init__.py
pmutt/io/cantera.py
pmutt/io/chemkin.py
pmutt/io/ctml_writer.py
pmutt/io/db.py
pmutt/io/excel.py
pmutt/io/gaussian.py
pmutt/io/json.py
pmutt/io/omkm.py
pmutt/io/ring.py
pmutt/io/thermdat.py
pmutt/io/vasp.py
pmutt/mixture/__init__.py
pmutt/mixture/cov.py
pmutt/omkm/__init__.py
pmutt/omkm/phase.py
pmutt/omkm/reaction.py
pmutt/omkm/units.py
pmutt/reaction/__init__.py
pmutt/reaction/bep.py
pmutt/reaction/network.py
pmutt/reaction/phasediagram.py
pmutt/statmech/__init__.py
pmutt/statmech/elec.py
pmutt/statmech/lsr.py
pmutt/statmech/nucl.py
pmutt/statmech/rot.py
pmutt/statmech/trans.py
pmutt/statmech/vib.py
pmutt/tests/__init__.py
pmutt/tests/test_constants.py
pmutt/tests/test_constants.xlsx
pmutt/tests/test_pMuTT.py
pmutt/tests/test_pmutt.xlsx
pmutt/tests/cantera/__init__.py
pmutt/tests/cantera/test_cantera.py
pmutt/tests/chemkin/__init__.py
pmutt/tests/empirical/__init__.py
pmutt/tests/empirical/test_pmutt_empirical_Nasa.py
pmutt/tests/empirical/test_pmutt_empirical_Nasa9.py
pmutt/tests/empirical/test_pmutt_empirical_empiricalbase.py
pmutt/tests/empirical/test_pmutt_empirical_lsr.py
pmutt/tests/empirical/test_pmutt_empirical_references.py
pmutt/tests/empirical/test_pmutt_empirical_shomate.py
pmutt/tests/eos/__init__.py
pmutt/tests/eos/test_pmutt_eos.py
pmutt/tests/equilibrium/__init__.py
pmutt/tests/equilibrium/test_pmutt_equilibrium.py
pmutt/tests/input_output/__init__.py
pmutt/tests/input_output/test_OUTCAR
pmutt/tests/input_output/test_gaussian.log
pmutt/tests/input_output/test_pmutt_io__thermdat.py
pmutt/tests/input_output/test_pmutt_io_gaussian.py
pmutt-1.4.17.dist-info/licenses/LICENSE.md
pmutt-1.4.17.dist-info/METADATA
pmutt-1.4.17.dist-info/WHEEL
pmutt-1.4.17.dist-info/top_level.txt
pmutt-1.4.17.dist-info/RECORD
