Metadata-Version: 2.4
Name: pmutt
Version: 1.4.17
Summary: Python Multiscale Thermochemistry Toolbox (pmutt)
Home-page: https://github.com/VlachosGroup/pmutt
Author: Vlachos Research Group
Author-email: vlachos@udel.edu
Classifier: Programming Language :: Python :: 3
Classifier: License :: OSI Approved :: MIT License
Classifier: Operating System :: OS Independent
Classifier: Intended Audience :: Science/Research
Classifier: Topic :: Scientific/Engineering :: Chemistry
License-File: LICENSE.md
Requires-Dist: ASE>=3.22.1
Requires-Dist: matplotlib>=3.5.0
Requires-Dist: numpy>=1.21.0
Requires-Dist: scipy>=1.7.0
Requires-Dist: pandas>=1.1.0
Requires-Dist: pymongo>=3.2.0
Requires-Dist: dnspython>=1.16.0
Requires-Dist: networkx>=2.6.0
Requires-Dist: pygal>=2.4.0
Requires-Dist: xlrd>=1.2.0
Requires-Dist: more_itertools>=8.14.0
Requires-Dist: PyYAML>=6.0.0
Requires-Dist: openpyxl>=3.0.10
Requires-Dist: pymatgen>=2025.5.2
Dynamic: author
Dynamic: author-email
Dynamic: classifier
Dynamic: description
Dynamic: description-content-type
Dynamic: home-page
Dynamic: license-file
Dynamic: requires-dist
Dynamic: summary
